langevitour/__about__.py
langevitour/__init__.py
langevitour/langevitour.py
langevitour/utils.py
langevitour/static/langevitour-pack.js
langevitour-0.8.0.dist-info/METADATA
langevitour-0.8.0.dist-info/WHEEL
langevitour-0.8.0.dist-info/licenses/LICENSE
langevitour-0.8.0.dist-info/licenses/LICENSE.md
langevitour-0.8.0.dist-info/RECORD
