Metadata-Version: 2.4
Name: langevitour
Version: 0.8.0
Summary: Python interface to langevintour
Project-URL: Documentation, https://github.com/pfh/langevitour#readme
Project-URL: Issues, https://github.com/pfh/langevitour/issues
Project-URL: Source, https://github.com/pfh/langevitour
Author-email: Wytamma Wirth <wytamma.wirth@me.com>, Paul Harrison <paul.harrison@monash.edu>
License-Expression: MIT
License-File: LICENSE
License-File: LICENSE.md
Classifier: Development Status :: 4 - Beta
Classifier: Programming Language :: Python
Classifier: Programming Language :: Python :: 3.7
Classifier: Programming Language :: Python :: 3.8
Classifier: Programming Language :: Python :: 3.9
Classifier: Programming Language :: Python :: 3.10
Classifier: Programming Language :: Python :: 3.11
Classifier: Programming Language :: Python :: Implementation :: CPython
Classifier: Programming Language :: Python :: Implementation :: PyPy
Requires-Python: >=3.7
Requires-Dist: numpy
